nylondetector/__init__.py
nylondetector/crawling/CrawlerNotebook.ipynb
nylondetector/crawling/SeleniumCrawler.ipynb
nylondetector/crawling/__init__.py
nylondetector/crawling/app_gnun_crawl_rvws.py
nylondetector/crawling/blog_hospital_crawler.py
nylondetector/crawling/cafe_crawl_each.py
nylondetector/crawling/cafe_crawl_srch_content.py
nylondetector/crawling/cafe_crawl_srch_url.py
nylondetector/crawling/cafe_get_each_info.py
nylondetector/crawling/cafe_get_srch_info.py
nylondetector/crawling/data/blog/백내장+부수입/url_original/blog_urls_백내장+부수입_from20210427_to20210527.csv
nylondetector/crawling/data/blog/백내장+부수입/url_original/blog_urls_백내장+부수입_from20210527_to20210627.csv
nylondetector/crawling/data/blog/백내장+부수입/url_original/blog_urls_백내장+부수입_from20210627_to20210727.csv
nylondetector/crawling/data/blog/백내장+부수입/url_original/blog_urls_백내장+부수입_from20210727_to20210827.csv
nylondetector/crawling/data/blog/백내장+부수입/url_original/blog_urls_백내장+부수입_from20210827_to20210927.csv
nylondetector/crawling/data/blog/백내장+부수입/url_original/blog_urls_백내장+부수입_from20210927_to20211027.csv
nylondetector/crawling/data/blog/백내장+부수입/url_original/blog_urls_백내장+부수입_from20211027_to20211127.csv
nylondetector/crawling/data/blog/백내장+부수입/url_original/blog_urls_백내장+부수입_from20211127_to20211227.csv
nylondetector/crawling/data/blog/백내장+부수입/url_original/blog_urls_백내장+부수입_from20211227_to20220127.csv
nylondetector/crawling/data/blog/백내장+부수입/url_original/blog_urls_백내장+부수입_from20220127_to20220227.csv
nylondetector/crawling/data/blog/백내장+부수입/url_original/blog_urls_백내장+부수입_from20220227_to20220327.csv
nylondetector/crawling/data/blog/백내장+부수입/url_original/blog_urls_백내장+부수입_from20220327_to20220427.csv
nylondetector/crawling/data/blog/백내장+소개/url_original/blog_urls_백내장+소개_from20210427_to20210527.csv
nylondetector/crawling/data/blog/백내장+소개/url_original/blog_urls_백내장+소개_from20210527_to20210627.csv
nylondetector/crawling/data/blog/백내장+소개/url_original/blog_urls_백내장+소개_from20210627_to20210727.csv
nylondetector-0.1.7.dist-info/WHEEL
nylondetector-0.1.7.dist-info/METADATA
nylondetector-0.1.7.dist-info/RECORD
