Metadata-Version: 2.1
Name: nylondetector
Version: 0.1.7
Summary: 
Author: Kwangsik Lee
Author-email: lks21c@gmail.com
Requires-Python: >=3.8,<4.0
Classifier: Programming Language :: Python :: 3
Classifier: Programming Language :: Python :: 3.10
Classifier: Programming Language :: Python :: 3.8
Classifier: Programming Language :: Python :: 3.9
Requires-Dist: aiohttp (>=3.8.1,<4.0.0)
Requires-Dist: baram (>=0.1.6,<0.2.0)
Requires-Dist: beautifulsoup4 (>=4.11.1,<5.0.0)
Requires-Dist: fire (>=0.4.0,<0.5.0)
Requires-Dist: nest-asyncio (>=1.5.5,<2.0.0)
Requires-Dist: pytest-cov (>=3.0.0,<4.0.0)
Requires-Dist: requests (>=2.27.1,<3.0.0)
Requires-Dist: tqdm (>=4.64.0,<5.0.0)
Requires-Dist: ujson (>=5.2.0,<6.0.0)
